vkpoint_api/__init__.py
vkpoint_api/vkpoint_api.py
vkpoint_api-2.0.8.dist-info/LICENSE
vkpoint_api-2.0.8.dist-info/METADATA
vkpoint_api-2.0.8.dist-info/WHEEL
vkpoint_api-2.0.8.dist-info/top_level.txt
vkpoint_api-2.0.8.dist-info/RECORD
