Metadata-Version: 2.1
Name: vkpoint-api
Version: 2.0.8
Summary: vkpoint - это python модуль для работы с монетой VK Point (VK Point API wrapper)
Home-page: https://github.com/Hcerk/vkpoint
Author: Hcerk
License: Apache License, Version 2.0, see LICENSE file
Download-URL: https://github.com/Hcerk/vkpoint/archive/v2.0.8.zip
Platform: UNKNOWN
Classifier: License :: OSI Approved :: Apache Software License
Classifier: Operating System :: OS Independent
Classifier: Programming Language :: Python
Classifier: Programming Language :: Python :: 3.6
Classifier: Programming Language :: Python :: 3.7
Classifier: Programming Language :: Python :: 3.8
Classifier: Programming Language :: Python :: Implementation :: PyPy
Classifier: Programming Language :: Python :: Implementation :: CPython
Requires-Dist: requests
Requires-Dist: six
